{
  "Items": [
    {
      "name": "Sir Alwyn Williams",
      "inner": [{
            "points": [{"x" : "55.8740145", "y" : "-4.2920211"},
            {"x" : "55.8740176", "y" : "-4.2917896"},
            {"x" : "55.8740208", "y" : "-4.2915686"},
            {"x" : "55.8739457", "y" : "-4.2914601"},
            {"x" : "55.8737967", "y" : "-4.2918125"},
            {"x" : "55.8738249", "y" : "-4.2918538"},
            {"x" : "55.8737938", "y" : "-4.2919222"},
            {"x" : "55.8739423", "y" : "-4.2921254"},
            {"x" : "55.8739684", "y" : "-4.2920657"},
            {"x" : "55.8739947", "y" : "-4.2920999"},
            {"x" : "55.8739961", "y" : "-4.2920208"},
            {"x" : "55.8740145", "y" : "-4.2920211"}]}
          ],
       "outer": [
            {"points": [{"x" : "55.8737656", "y" : "-4.2918839"},
            {"x" : "55.8734231", "y" : "-4.2923585"},
            {"x" : "55.8735321", "y" : "-4.2923649"},
            {"x" : "55.8736780", "y" : "-4.2925566"},
            {"x" : "55.8737405", "y" : "-4.2923991"},
            {"x" : "55.8738346", "y" : "-4.2925296"},
            {"x" : "55.8739703", "y" : "-4.2924963"},
            {"x" : "55.8742697", "y" : "-4.2920739"},
            {"x" : "55.8740346", "y" : "-4.2912523"},
            {"x" : "55.8737656", "y" : "-4.2918839"}]}
          ]
      ,
      "Clue": "A place surrounded by some of the Universities less flattering buildings",
      "Information": "The Sir Alwyn Williams Building at the University of Glasgow was opened on 22 June 2007 by Professor Anne Glover, Chief Scientific Adviser for Scotland, and Williams's widow, Joan. It was an extension to the facilities of the Department of Computing Science, located between the Department's pre-existing accommodation, in a row of interconnected Victorian townhouses on Lilybank Gardens, and the 1968-built Queen Margaret Union building. The Building contains offices and laboratories as well as informal 'break-out spaces'."
    },
    {
        "name": "Advanced Research Centre",
        "inner": [
          {"points": [{"x" : "55.8710654", "y" : "-4.2961992"},
          {"x" : "55.8711575", "y" : "-4.2953952"},
          {"x" : "55.8712233", "y" : "-4.2953874"},
          {"x" : "55.8713032", "y" : "-4.2955417"},
          {"x" : "55.8714116", "y" : "-4.2953635"},
          {"x" : "55.8716196", "y" : "-4.2953485"},
          {"x" : "55.8717141", "y" : "-4.295472"},
          {"x" : "55.8717635", "y" : "-4.2953518"},
          {"x" : "55.8718499", "y" : "-4.2953559"},
          {"x" : "55.8720463", "y" : "-4.29559"},
          {"x" : "55.8720684", "y" : "-4.2960436"},
          {"x" : "55.8710654", "y" : "-4.2961992"}]}
          ],
          "outer": [
          {"points": [{"x" : "55.8710654", "y" : "-4.2961992"},
          {"x" : "55.8711088", "y" : "-4.2953565"},
          {"x" : "55.8711198", "y" : "-4.2946853"},
          {"x" : "55.8720453", "y" : "-4.2947023"},
          {"x" : "55.8720534", "y" : "-4.2952395"},
          {"x" : "55.8720684", "y" : "-4.2960436"}]}
        ],
    "Clue": "Named after the founder of one of India's biggest biotechnology companies",
    "Information": "The Mazumdar-Shaw Advanced Research Centre (ARC) building houses 500 multidisciplinary researchers and serves as a centerpiece of the University’s new campus development in Glasgow, Scotland."
    },
    {
      "name": "Gilbert Scott",
      "inner": [
        {"points": [{"x" : "55.871994" , "y" : "-4.2896235"},
        {"x" : "55.8719913" , "y" : "-4.2896022"},
        {"x" : "55.8719812" , "y" : "-4.2896069"},
        {"x" : "55.8719697" , "y" : "-4.2895221"},
        {"x" : "55.8719806" , "y" : "-4.2895184"},
        {"x" : "55.8719781" , "y" : "-4.2894983"},
        {"x" : "55.8719689" , "y" : "-4.2895023"},
        {"x" : "55.8719567" , "y" : "-4.2894235"},
        {"x" : "55.8719678" , "y" : "-4.2894188"},
        {"x" : "55.8719651" , "y" : "-4.2893961"},
        {"x" : "55.8719543" , "y" : "-4.2894007"},
        {"x" : "55.8719512" , "y" : "-4.2893806"},
        {"x" : "55.87194" , "y" : "-4.289386"},
        {"x" : "55.8719422" , "y" : "-4.2894024"},
        {"x" : "55.871937" , "y" : "-4.2894043"},
        {"x" : "55.8719271" , "y" : "-4.2893325"},
        {"x" : "55.87192" , "y" : "-4.2892737"},
        {"x" : "55.8719497" , "y" : "-4.2892614"},
        {"x" : "55.8719525" , "y" : "-4.2892825"},
        {"x" : "55.8719658" , "y" : "-4.289277"},
        {"x" : "55.8719629" , "y" : "-4.289255"},
        {"x" : "55.871972" , "y" : "-4.2892512"},
        {"x" : "55.8719693" , "y" : "-4.289231"},
        {"x" : "55.8719598" , "y" : "-4.289235"},
        {"x" : "55.8719505" , "y" : "-4.2891635"},
        {"x" : "55.8719597" , "y" : "-4.2891597"},
        {"x" : "55.8719568" , "y" : "-4.2891371"},
        {"x" : "55.8719478" , "y" : "-4.2891408"},
        {"x" : "55.8719393" , "y" : "-4.2890758"},
        {"x" : "55.8719486" , "y" : "-4.289072"},
        {"x" : "55.8719457" , "y" : "-4.2890498"},
        {"x" : "55.871936" , "y" : "-4.2890538"},
        {"x" : "55.8719272" , "y" : "-4.2889864"},
        {"x" : "55.8719369" , "y" : "-4.2889823"},
        {"x" : "55.8719339" , "y" : "-4.2889596"},
        {"x" : "55.8719251" , "y" : "-4.2889633"},
        {"x" : "55.8719169" , "y" : "-4.2889003"},
        {"x" : "55.8719259" , "y" : "-4.2888966"},
        {"x" : "55.8719232" , "y" : "-4.2888763"},
        {"x" : "55.8719143" , "y" : "-4.28888"},
        {"x" : "55.8719057" , "y" : "-4.288814"},
        {"x" : "55.8719148" , "y" : "-4.2888102"},
        {"x" : "55.8719122" , "y" : "-4.2887904"},
        {"x" : "55.8719025" , "y" : "-4.2887944"},
        {"x" : "55.8718937" , "y" : "-4.2887269"},
        {"x" : "55.8719037" , "y" : "-4.2887227"},
        {"x" : "55.871901" , "y" : "-4.2887018"},
        {"x" : "55.8718908" , "y" : "-4.288706"},
        {"x" : "55.8718815" , "y" : "-4.2886345"},
        {"x" : "55.8718916" , "y" : "-4.2886303"},
        {"x" : "55.8718887" , "y" : "-4.2886083"},
        {"x" : "55.8718763" , "y" : "-4.2886134"},
        {"x" : "55.871872" , "y" : "-4.288579"},
        {"x" : "55.8718754" , "y" : "-4.2885778"},
        {"x" : "55.8718734" , "y" : "-4.2885609"},
        {"x" : "55.8718697" , "y" : "-4.2885624"},
        {"x" : "55.8718672" , "y" : "-4.2885436"},
        {"x" : "55.8718651" , "y" : "-4.2885241"},
        {"x" : "55.8718682" , "y" : "-4.288523"},
        {"x" : "55.8718655" , "y" : "-4.2885035"},
        {"x" : "55.871862" , "y" : "-4.288505"},
        {"x" : "55.8718597" , "y" : "-4.2884906"},
        {"x" : "55.8718934" , "y" : "-4.288477"},
        {"x" : "55.8718879" , "y" : "-4.288438"},
        {"x" : "55.8718904" , "y" : "-4.2884398"},
        {"x" : "55.8718943" , "y" : "-4.2884393"},
        {"x" : "55.8718964" , "y" : "-4.2884363"},
        {"x" : "55.8719156" , "y" : "-4.2884055"},
        {"x" : "55.871919" , "y" : "-4.2884083"},
        {"x" : "55.8719223" , "y" : "-4.288406"},
        {"x" : "55.8719245" , "y" : "-4.2884006"},
        {"x" : "55.8719248" , "y" : "-4.2883952"},
        {"x" : "55.8719225" , "y" : "-4.2883904"},
        {"x" : "55.8719265" , "y" : "-4.2883734"},
        {"x" : "55.8719281" , "y" : "-4.2883597"},
        {"x" : "55.8719314" , "y" : "-4.2883594"},
        {"x" : "55.8719344" , "y" : "-4.2883547"},
        {"x" : "55.8719352" , "y" : "-4.288348"},
        {"x" : "55.8719337" , "y" : "-4.2883411"},
        {"x" : "55.8719304" , "y" : "-4.2883397"},
        {"x" : "55.8719289" , "y" : "-4.288323"},
        {"x" : "55.8719263" , "y" : "-4.2883062"},
        {"x" : "55.8719283" , "y" : "-4.2883014"},
        {"x" : "55.8719288" , "y" : "-4.2882943"},
        {"x" : "55.8719263" , "y" : "-4.2882888"},
        {"x" : "55.8719237" , "y" : "-4.2882876"},
        {"x" : "55.8719205" , "y" : "-4.2882888"},
        {"x" : "55.8719121" , "y" : "-4.2882732"},
        {"x" : "55.8719026" , "y" : "-4.2882596"},
        {"x" : "55.8719019" , "y" : "-4.2882529"},
        {"x" : "55.8718996" , "y" : "-4.2882479"},
        {"x" : "55.8718959" , "y" : "-4.2882469"},
        {"x" : "55.8718926" , "y" : "-4.2882496"},
        {"x" : "55.8718908" , "y" : "-4.2882531"},
        {"x" : "55.8718745" , "y" : "-4.2882506"},
        {"x" : "55.871873" , "y" : "-4.2882442"},
        {"x" : "55.8718689" , "y" : "-4.288241"},
        {"x" : "55.8718653" , "y" : "-4.2882413"},
        {"x" : "55.8718619" , "y" : "-4.2882464"},
        {"x" : "55.8718561" , "y" : "-4.2882029"},
        {"x" : "55.8718239" , "y" : "-4.2882175"},
        {"x" : "55.8718209" , "y" : "-4.2881931"},
        {"x" : "55.8718244" , "y" : "-4.2881916"},
        {"x" : "55.8718217" , "y" : "-4.2881718"},
        {"x" : "55.8718182" , "y" : "-4.2881733"},
        {"x" : "55.8718134" , "y" : "-4.2881394"},
        {"x" : "55.8718171" , "y" : "-4.2881381"},
        {"x" : "55.8718135" , "y" : "-4.2881118"},
        {"x" : "55.8718098" , "y" : "-4.2881133"},
        {"x" : "55.8718067" , "y" : "-4.288091"},
        {"x" : "55.8718194" , "y" : "-4.2880857"},
        {"x" : "55.8718163" , "y" : "-4.2880627"},
        {"x" : "55.8718059" , "y" : "-4.288067"},
        {"x" : "55.871797" , "y" : "-4.2879996"},
        {"x" : "55.8718073" , "y" : "-4.2879953"},
        {"x" : "55.871804" , "y" : "-4.28797"},
        {"x" : "55.8717947" , "y" : "-4.2879739"},
        {"x" : "55.8717863" , "y" : "-4.2879109"},
        {"x" : "55.8717959" , "y" : "-4.2879068"},
        {"x" : "55.8717931" , "y" : "-4.2878857"},
        {"x" : "55.8717836" , "y" : "-4.2878897"},
        {"x" : "55.8717747" , "y" : "-4.287822"},
        {"x" : "55.8717838" , "y" : "-4.2878181"},
        {"x" : "55.871781" , "y" : "-4.287797"},
        {"x" : "55.8717713" , "y" : "-4.287801"},
        {"x" : "55.8717627" , "y" : "-4.2877353"},
        {"x" : "55.871773" , "y" : "-4.2877309"},
        {"x" : "55.8717699" , "y" : "-4.2877074"},
        {"x" : "55.8717594" , "y" : "-4.2877118"},
        {"x" : "55.871751" , "y" : "-4.2876483"},
        {"x" : "55.8717619" , "y" : "-4.2876438"},
        {"x" : "55.8717587" , "y" : "-4.2876195"},
        {"x" : "55.8717476" , "y" : "-4.2876241"},
        {"x" : "55.8717391" , "y" : "-4.2875595"},
        {"x" : "55.8717495" , "y" : "-4.2875551"},
        {"x" : "55.871747" , "y" : "-4.2875365"},
        {"x" : "55.8717366" , "y" : "-4.2875408"},
        {"x" : "55.8717274" , "y" : "-4.2874713"},
        {"x" : "55.8717373" , "y" : "-4.2874671"},
        {"x" : "55.8717346" , "y" : "-4.2874467"},
        {"x" : "55.8717228" , "y" : "-4.2874516"},
        {"x" : "55.8717197" , "y" : "-4.2874287"},
        {"x" : "55.8717082" , "y" : "-4.2874335"},
        {"x" : "55.8717112" , "y" : "-4.2874562"},
        {"x" : "55.8716864" , "y" : "-4.2874666"},
        {"x" : "55.8716722" , "y" : "-4.2873475"},
        {"x" : "55.8716825" , "y" : "-4.2873433"},
        {"x" : "55.8716804" , "y" : "-4.2873268"},
        {"x" : "55.871689" , "y" : "-4.2873234"},
        {"x" : "55.8716862" , "y" : "-4.2873011"},
        {"x" : "55.8716776" , "y" : "-4.2873045"},
        {"x" : "55.8716671" , "y" : "-4.2872214"},
        {"x" : "55.8716755" , "y" : "-4.2872181"},
        {"x" : "55.8716729" , "y" : "-4.2871973"},
        {"x" : "55.8716647" , "y" : "-4.2872006"},
        {"x" : "55.8716549" , "y" : "-4.2871233"},
        {"x" : "55.8716637" , "y" : "-4.2871198"},
        {"x" : "55.8716604" , "y" : "-4.2870937"},
        {"x" : "55.8716496" , "y" : "-4.287098"},
        {"x" : "55.8716479" , "y" : "-4.2870843"},
        {"x" : "55.871636" , "y" : "-4.2870891"},
        {"x" : "55.8716378" , "y" : "-4.2871034"},
        {"x" : "55.8716112" , "y" : "-4.2871141"},
        {"x" : "55.8716096" , "y" : "-4.2871013"},
        {"x" : "55.871598" , "y" : "-4.2871059"},
        {"x" : "55.8715996" , "y" : "-4.2871185"},
        {"x" : "55.871575" , "y" : "-4.2871284"},
        {"x" : "55.8715733" , "y" : "-4.2871149"},
        {"x" : "55.8715599" , "y" : "-4.2871203"},
        {"x" : "55.8715615" , "y" : "-4.2871333"},
        {"x" : "55.8715376" , "y" : "-4.2871429"},
        {"x" : "55.871536" , "y" : "-4.2871299"},
        {"x" : "55.8715223" , "y" : "-4.2871354"},
        {"x" : "55.8715252" , "y" : "-4.2871613"},
        {"x" : "55.8712034" , "y" : "-4.2872927"},
        {"x" : "55.8710609" , "y" : "-4.2873498"},
        {"x" : "55.8710593" , "y" : "-4.2873391"},
        {"x" : "55.8710563" , "y" : "-4.2873493"},
        {"x" : "55.8710521" , "y" : "-4.2873579"},
        {"x" : "55.8710436" , "y" : "-4.2873649"},
        {"x" : "55.8710347" , "y" : "-4.2873657"},
        {"x" : "55.8710299" , "y" : "-4.2873641"},
        {"x" : "55.8710212" , "y" : "-4.287356"},
        {"x" : "55.8709932" , "y" : "-4.2873659"},
        {"x" : "55.8709911" , "y" : "-4.2873492"},
        {"x" : "55.8709795" , "y" : "-4.2873535"},
        {"x" : "55.870981" , "y" : "-4.2873713"},
        {"x" : "55.870955" , "y" : "-4.2873817"},
        {"x" : "55.8709533" , "y" : "-4.2873649"},
        {"x" : "55.8709396" , "y" : "-4.2873693"},
        {"x" : "55.8709415" , "y" : "-4.2873874"},
        {"x" : "55.8709165" , "y" : "-4.2873978"},
        {"x" : "55.8709138" , "y" : "-4.2873787"},
        {"x" : "55.870902" , "y" : "-4.287383"},
        {"x" : "55.8709042" , "y" : "-4.2874025"},
        {"x" : "55.8708961" , "y" : "-4.2874055"},
        {"x" : "55.8708986" , "y" : "-4.2874297"},
        {"x" : "55.8709078" , "y" : "-4.2874263"},
        {"x" : "55.8709183" , "y" : "-4.2875057"},
        {"x" : "55.8709091" , "y" : "-4.2875091"},
        {"x" : "55.8709116" , "y" : "-4.2875329"},
        {"x" : "55.8709215" , "y" : "-4.2875289"},
        {"x" : "55.8709315" , "y" : "-4.2876077"},
        {"x" : "55.8709215" , "y" : "-4.2876114"},
        {"x" : "55.8709244" , "y" : "-4.2876315"},
        {"x" : "55.8709351" , "y" : "-4.2876278"},
        {"x" : "55.8709365" , "y" : "-4.2876377"},
        {"x" : "55.870945" , "y" : "-4.2876342"},
        {"x" : "55.8709509" , "y" : "-4.2876774"},
        {"x" : "55.8709428" , "y" : "-4.2876794"},
        {"x" : "55.8709452" , "y" : "-4.2876992"},
        {"x" : "55.8709531" , "y" : "-4.2876955"},
        {"x" : "55.8709772" , "y" : "-4.2878826"},
        {"x" : "55.8709681" , "y" : "-4.2878868"},
        {"x" : "55.8709702" , "y" : "-4.2879029"},
        {"x" : "55.8709793" , "y" : "-4.2878997"},
        {"x" : "55.8709846" , "y" : "-4.2879396"},
        {"x" : "55.8709761" , "y" : "-4.2879426"},
        {"x" : "55.8709778" , "y" : "-4.287956"},
        {"x" : "55.8709744" , "y" : "-4.2879574"},
        {"x" : "55.8709753" , "y" : "-4.2879632"},
        {"x" : "55.8709688" , "y" : "-4.2879662"},
        {"x" : "55.8709707" , "y" : "-4.2879812"},
        {"x" : "55.8709775" , "y" : "-4.2879792"},
        {"x" : "55.8709838" , "y" : "-4.2880244"},
        {"x" : "55.8709889" , "y" : "-4.2880653"},
        {"x" : "55.8709813" , "y" : "-4.2880677"},
        {"x" : "55.870983" , "y" : "-4.2880818"},
        {"x" : "55.8709909" , "y" : "-4.2880796"},
        {"x" : "55.8709915" , "y" : "-4.2880876"},
        {"x" : "55.8709964" , "y" : "-4.2880861"},
        {"x" : "55.8709973" , "y" : "-4.2880953"},
        {"x" : "55.8710053" , "y" : "-4.2880928"},
        {"x" : "55.87101" , "y" : "-4.2881347"},
        {"x" : "55.871003" , "y" : "-4.2881374"},
        {"x" : "55.8710045" , "y" : "-4.2881527"},
        {"x" : "55.8710117" , "y" : "-4.28815"},
        {"x" : "55.871016" , "y" : "-4.2881922"},
        {"x" : "55.8710095" , "y" : "-4.2881947"},
        {"x" : "55.8710107" , "y" : "-4.288208"},
        {"x" : "55.8710179" , "y" : "-4.2882058"},
        {"x" : "55.8710232" , "y" : "-4.2882479"},
        {"x" : "55.8710156" , "y" : "-4.2882507"},
        {"x" : "55.8710172" , "y" : "-4.288264"},
        {"x" : "55.8710247" , "y" : "-4.2882603"},
        {"x" : "55.8710302" , "y" : "-4.2883024"},
        {"x" : "55.8710228" , "y" : "-4.2883057"},
        {"x" : "55.8710246" , "y" : "-4.2883181"},
        {"x" : "55.8710321" , "y" : "-4.2883148"},
        {"x" : "55.8710381" , "y" : "-4.2883597"},
        {"x" : "55.8710296" , "y" : "-4.2883636"},
        {"x" : "55.8710316" , "y" : "-4.2883786"},
        {"x" : "55.8710403" , "y" : "-4.2883749"},
        {"x" : "55.8710455" , "y" : "-4.2884141"},
        {"x" : "55.8710358" , "y" : "-4.288418"},
        {"x" : "55.8710279" , "y" : "-4.288408"},
        {"x" : "55.8710225" , "y" : "-4.2884219"},
        {"x" : "55.8710321" , "y" : "-4.2884348"},
        {"x" : "55.8710404" , "y" : "-4.2885045"},
        {"x" : "55.8710334" , "y" : "-4.2885074"},
        {"x" : "55.8710355" , "y" : "-4.2885235"},
        {"x" : "55.8710427" , "y" : "-4.288521"},
        {"x" : "55.8710513" , "y" : "-4.2885845"},
        {"x" : "55.8710337" , "y" : "-4.2885918"},
        {"x" : "55.8710375" , "y" : "-4.2886202"},
        {"x" : "55.8710346" , "y" : "-4.2886215"},
        {"x" : "55.8710318" , "y" : "-4.2886249"},
        {"x" : "55.8710315" , "y" : "-4.2886294"},
        {"x" : "55.8710335" , "y" : "-4.2886338"},
        {"x" : "55.871036" , "y" : "-4.2886342"},
        {"x" : "55.8710392" , "y" : "-4.2886333"},
        {"x" : "55.8710442" , "y" : "-4.2886719"},
        {"x" : "55.8710506" , "y" : "-4.2887208"},
        {"x" : "55.8710471" , "y" : "-4.2887224"},
        {"x" : "55.8710448" , "y" : "-4.2887254"},
        {"x" : "55.8710444" , "y" : "-4.2887299"},
        {"x" : "55.8710461" , "y" : "-4.2887333"},
        {"x" : "55.8710488" , "y" : "-4.2887339"},
        {"x" : "55.871052" , "y" : "-4.2887326"},
        {"x" : "55.8710558" , "y" : "-4.2887607"},
        {"x" : "55.8710718" , "y" : "-4.2887541"},
        {"x" : "55.8710808" , "y" : "-4.2888189"},
        {"x" : "55.8710727" , "y" : "-4.2888217"},
        {"x" : "55.8710759" , "y" : "-4.2888435"},
        {"x" : "55.8710839" , "y" : "-4.2888403"},
        {"x" : "55.8710923" , "y" : "-4.2889022"},
        {"x" : "55.871086" , "y" : "-4.2889189"},
        {"x" : "55.8710943" , "y" : "-4.2889282"},
        {"x" : "55.8710995" , "y" : "-4.2889134"},
        {"x" : "55.8711106" , "y" : "-4.2889089"},
        {"x" : "55.8711211" , "y" : "-4.2889883"},
        {"x" : "55.871114" , "y" : "-4.2889914"},
        {"x" : "55.8711159" , "y" : "-4.2890064"},
        {"x" : "55.871123" , "y" : "-4.2890041"},
        {"x" : "55.8711424" , "y" : "-4.2891509"},
        {"x" : "55.8711347" , "y" : "-4.2891536"},
        {"x" : "55.8711364" , "y" : "-4.2891667"},
        {"x" : "55.8711443" , "y" : "-4.289164"},
        {"x" : "55.8711537" , "y" : "-4.2892358"},
        {"x" : "55.8711433" , "y" : "-4.2892395"},
        {"x" : "55.8711445" , "y" : "-4.28925"},
        {"x" : "55.8711418" , "y" : "-4.2892505"},
        {"x" : "55.8711423" , "y" : "-4.2892554"},
        {"x" : "55.871137" , "y" : "-4.2892571"},
        {"x" : "55.8711387" , "y" : "-4.289272"},
        {"x" : "55.8711448" , "y" : "-4.2892696"},
        {"x" : "55.8711507" , "y" : "-4.2893175"},
        {"x" : "55.8711559" , "y" : "-4.2893586"},
        {"x" : "55.8711505" , "y" : "-4.2893607"},
        {"x" : "55.8711525" , "y" : "-4.2893757"},
        {"x" : "55.8711582" , "y" : "-4.2893732"},
        {"x" : "55.8711589" , "y" : "-4.2893789"},
        {"x" : "55.8711619" , "y" : "-4.2893776"},
        {"x" : "55.8711632" , "y" : "-4.2893883"},
        {"x" : "55.8711723" , "y" : "-4.2893836"},
        {"x" : "55.8711794" , "y" : "-4.2894329"},
        {"x" : "55.8711702" , "y" : "-4.2894359"},
        {"x" : "55.8711719" , "y" : "-4.2894477"},
        {"x" : "55.8711809" , "y" : "-4.2894457"},
        {"x" : "55.8711883" , "y" : "-4.2894959"},
        {"x" : "55.8711793" , "y" : "-4.289498"},
        {"x" : "55.8711811" , "y" : "-4.2895154"},
        {"x" : "55.8711898" , "y" : "-4.289512"},
        {"x" : "55.8711954" , "y" : "-4.2895556"},
        {"x" : "55.8711866" , "y" : "-4.2895593"},
        {"x" : "55.8711892" , "y" : "-4.2895781"},
        {"x" : "55.8711983" , "y" : "-4.2895747"},
        {"x" : "55.8712039" , "y" : "-4.2896175"},
        {"x" : "55.8711952" , "y" : "-4.289621"},
        {"x" : "55.8711975" , "y" : "-4.2896358"},
        {"x" : "55.8712058" , "y" : "-4.2896331"},
        {"x" : "55.8712131" , "y" : "-4.2896911"},
        {"x" : "55.8712067" , "y" : "-4.2896931"},
        {"x" : "55.8712083" , "y" : "-4.2897091"},
        {"x" : "55.8711977" , "y" : "-4.2897119"},
        {"x" : "55.8711992" , "y" : "-4.2897249"},
        {"x" : "55.8711943" , "y" : "-4.2897263"},
        {"x" : "55.871184" , "y" : "-4.2897581"},
        {"x" : "55.8711892" , "y" : "-4.2897953"},
        {"x" : "55.8712067" , "y" : "-4.2898168"},
        {"x" : "55.8712116" , "y" : "-4.2898151"},
        {"x" : "55.8712127" , "y" : "-4.2898265"},
        {"x" : "55.8712236" , "y" : "-4.2898242"},
        {"x" : "55.8712362" , "y" : "-4.2899154"},
        {"x" : "55.8712267" , "y" : "-4.2899181"},
        {"x" : "55.8712285" , "y" : "-4.2899335"},
        {"x" : "55.8712374" , "y" : "-4.2899298"},
        {"x" : "55.8712393" , "y" : "-4.2899442"},
        {"x" : "55.8712471" , "y" : "-4.28994"},
        {"x" : "55.8712457" , "y" : "-4.2899281"},
        {"x" : "55.8712754" , "y" : "-4.2899144"},
        {"x" : "55.8712773" , "y" : "-4.2899278"},
        {"x" : "55.8712838" , "y" : "-4.2899244"},
        {"x" : "55.8712829" , "y" : "-4.2899117"},
        {"x" : "55.8713119" , "y" : "-4.2898993"},
        {"x" : "55.8713136" , "y" : "-4.289912"},
        {"x" : "55.8713222" , "y" : "-4.2899083"},
        {"x" : "55.8713207" , "y" : "-4.2898949"},
        {"x" : "55.8713516" , "y" : "-4.2898825"},
        {"x" : "55.8713531" , "y" : "-4.2898966"},
        {"x" : "55.8713617" , "y" : "-4.2898919"},
        {"x" : "55.8713602" , "y" : "-4.2898788"},
        {"x" : "55.8713826" , "y" : "-4.2898693"},
        {"x" : "55.871386" , "y" : "-4.2898969"},
        {"x" : "55.8713995" , "y" : "-4.2898909"},
        {"x" : "55.8713943" , "y" : "-4.289858"},
        {"x" : "55.8714262" , "y" : "-4.2898426"},
        {"x" : "55.8714308" , "y" : "-4.2898735"},
        {"x" : "55.8714424" , "y" : "-4.2898668"},
        {"x" : "55.8714383" , "y" : "-4.2898379"},
        {"x" : "55.8714688" , "y" : "-4.2898238"},
        {"x" : "55.8714725" , "y" : "-4.2898533"},
        {"x" : "55.8714861" , "y" : "-4.2898487"},
        {"x" : "55.8714815" , "y" : "-4.2898185"},
        {"x" : "55.8715138" , "y" : "-4.2898052"},
        {"x" : "55.8715506" , "y" : "-4.2897901"},
        {"x" : "55.8715617" , "y" : "-4.289787"},
        {"x" : "55.8715824" , "y" : "-4.2899345"},
        {"x" : "55.8715959" , "y" : "-4.2899298"},
        {"x" : "55.8715918" , "y" : "-4.2898976"},
        {"x" : "55.8716174" , "y" : "-4.2898882"},
        {"x" : "55.8716219" , "y" : "-4.2899291"},
        {"x" : "55.8716354" , "y" : "-4.2899238"},
        {"x" : "55.8716309" , "y" : "-4.2898835"},
        {"x" : "55.8716617" , "y" : "-4.2898708"},
        {"x" : "55.8716644" , "y" : "-4.2898949"},
        {"x" : "55.8716779" , "y" : "-4.2898889"},
        {"x" : "55.8716581" , "y" : "-4.2897471"},
        {"x" : "55.871683" , "y" : "-4.2897376"},
        {"x" : "55.8717004" , "y" : "-4.28973"},
        {"x" : "55.8717298" , "y" : "-4.2897172"},
        {"x" : "55.8717344" , "y" : "-4.2897508"},
        {"x" : "55.8717487" , "y" : "-4.2897454"},
        {"x" : "55.8717441" , "y" : "-4.2897125"},
        {"x" : "55.871775" , "y" : "-4.2896991"},
        {"x" : "55.8717791" , "y" : "-4.28973"},
        {"x" : "55.8717923" , "y" : "-4.2897239"},
        {"x" : "55.8717882" , "y" : "-4.2896951"},
        {"x" : "55.8718205" , "y" : "-4.2896797"},
        {"x" : "55.8718246" , "y" : "-4.2897129"},
        {"x" : "55.8718361" , "y" : "-4.2897068"},
        {"x" : "55.8718338" , "y" : "-4.2896911"},
        {"x" : "55.8718568" , "y" : "-4.289682"},
        {"x" : "55.8718585" , "y" : "-4.2896978"},
        {"x" : "55.8718704" , "y" : "-4.2896931"},
        {"x" : "55.8718683" , "y" : "-4.2896757"},
        {"x" : "55.8718946" , "y" : "-4.2896653"},
        {"x" : "55.8718971" , "y" : "-4.289682"},
        {"x" : "55.8719106" , "y" : "-4.2896763"},
        {"x" : "55.8719087" , "y" : "-4.2896592"},
        {"x" : "55.8719345" , "y" : "-4.2896482"},
        {"x" : "55.8719364" , "y" : "-4.2896649"},
        {"x" : "55.8719469" , "y" : "-4.2896616"},
        {"x" : "55.8719456" , "y" : "-4.2896431"},
        {"x" : "55.8719689" , "y" : "-4.2896341"},
        {"x" : "55.8719712" , "y" : "-4.2896508"},
        {"x" : "55.8719855" , "y" : "-4.2896448"},
        {"x" : "55.8719832" , "y" : "-4.2896274"},
        {"x" : "55.871994" , "y" : "-4.2896235"}]}
       ],
       "outer": [
        {"points": [
        {"x" : "55.8712115" , "y" : "-4.2887517"},
        {"x" : "55.871226" , "y" : "-4.2888641"},
        {"x" : "55.8712168" , "y" : "-4.2888672"},
        {"x" : "55.8712485" , "y" : "-4.2891053"},
        {"x" : "55.8712554" , "y" : "-4.289103"},
        {"x" : "55.8712571" , "y" : "-4.2891171"},
        {"x" : "55.8712494" , "y" : "-4.2891184"},
        {"x" : "55.8712607" , "y" : "-4.2892073"},
        {"x" : "55.8712639" , "y" : "-4.2892066"},
        {"x" : "55.8712799" , "y" : "-4.2893253"},
        {"x" : "55.8712763" , "y" : "-4.289327"},
        {"x" : "55.8713172" , "y" : "-4.2896239"},
        {"x" : "55.8713488" , "y" : "-4.28961"},
        {"x" : "55.871515" , "y" : "-4.289534"},
        {"x" : "55.8714956" , "y" : "-4.2893877"},
        {"x" : "55.8714834" , "y" : "-4.2893913"},
        {"x" : "55.8714785" , "y" : "-4.2893568"},
        {"x" : "55.8714977" , "y" : "-4.2893474"},
        {"x" : "55.8714881" , "y" : "-4.2892777"},
        {"x" : "55.8714956" , "y" : "-4.2892747"},
        {"x" : "55.8714928" , "y" : "-4.2892592"},
        {"x" : "55.8715071" , "y" : "-4.2892515"},
        {"x" : "55.8715096" , "y" : "-4.2892663"},
        {"x" : "55.8715265" , "y" : "-4.2892579"},
        {"x" : "55.8715246" , "y" : "-4.2892425"},
        {"x" : "55.8715434" , "y" : "-4.2892341"},
        {"x" : "55.8715459" , "y" : "-4.2892485"},
        {"x" : "55.8715637" , "y" : "-4.2892391"},
        {"x" : "55.8715622" , "y" : "-4.289226"},
        {"x" : "55.8715779" , "y" : "-4.2892177"},
        {"x" : "55.8715797" , "y" : "-4.2892371"},
        {"x" : "55.8715873" , "y" : "-4.2892331"},
        {"x" : "55.8715978" , "y" : "-4.2893122"},
        {"x" : "55.8716164" , "y" : "-4.2893039"},
        {"x" : "55.8716203" , "y" : "-4.289332"},
        {"x" : "55.871609" , "y" : "-4.2893366"},
        {"x" : "55.8716266" , "y" : "-4.2894839"},
        {"x" : "55.8717968" , "y" : "-4.289417"},
        {"x" : "55.8718209" , "y" : "-4.2894119"},
        {"x" : "55.8718348" , "y" : "-4.2893866"},
        {"x" : "55.8718247" , "y" : "-4.2893133"},
        {"x" : "55.8717933" , "y" : "-4.2893263"},
        {"x" : "55.8717953" , "y" : "-4.2893423"},
        {"x" : "55.8717864" , "y" : "-4.289346"},
        {"x" : "55.8717841" , "y" : "-4.2893281"},
        {"x" : "55.871771" , "y" : "-4.2893335"},
        {"x" : "55.8717684" , "y" : "-4.2893139"},
        {"x" : "55.8717789" , "y" : "-4.2893095"},
        {"x" : "55.8717696" , "y" : "-4.2892383"},
        {"x" : "55.8717598" , "y" : "-4.2892423"},
        {"x" : "55.871757" , "y" : "-4.2892205"},
        {"x" : "55.8717669" , "y" : "-4.2892164"},
        {"x" : "55.8717582" , "y" : "-4.2891492"},
        {"x" : "55.8717478" , "y" : "-4.2891535"},
        {"x" : "55.871745" , "y" : "-4.2891319"},
        {"x" : "55.8717554" , "y" : "-4.2891275"},
        {"x" : "55.8717467" , "y" : "-4.2890603"},
        {"x" : "55.871737" , "y" : "-4.2890643"},
        {"x" : "55.8717341" , "y" : "-4.2890419"},
        {"x" : "55.8717438" , "y" : "-4.2890379"},
        {"x" : "55.8717356" , "y" : "-4.2889748"},
        {"x" : "55.8717252" , "y" : "-4.288979"},
        {"x" : "55.8717223" , "y" : "-4.2889563"},
        {"x" : "55.8717327" , "y" : "-4.288952"},
        {"x" : "55.8717244" , "y" : "-4.2888885"},
        {"x" : "55.8717143" , "y" : "-4.2888927"},
        {"x" : "55.8717117" , "y" : "-4.2888724"},
        {"x" : "55.8717216" , "y" : "-4.2888683"},
        {"x" : "55.8717128" , "y" : "-4.2888012"},
        {"x" : "55.8717028" , "y" : "-4.2888053"},
        {"x" : "55.8717" , "y" : "-4.2887835"},
        {"x" : "55.8717098" , "y" : "-4.2887794"},
        {"x" : "55.8717006" , "y" : "-4.2887091"},
        {"x" : "55.8716904" , "y" : "-4.2887133"},
        {"x" : "55.8716874" , "y" : "-4.2886906"},
        {"x" : "55.8717002" , "y" : "-4.2886853"},
        {"x" : "55.8716973" , "y" : "-4.2886631"},
        {"x" : "55.8717083" , "y" : "-4.2886585"},
        {"x" : "55.8717114" , "y" : "-4.2886819"},
        {"x" : "55.8717395" , "y" : "-4.2886702"},
        {"x" : "55.871724" , "y" : "-4.2885423"},
        {"x" : "55.8716221" , "y" : "-4.2885826"},
        {"x" : "55.8716119" , "y" : "-4.2885916"},
        {"x" : "55.8716052" , "y" : "-4.2886054"},
        {"x" : "55.8716017" , "y" : "-4.2886253"},
        {"x" : "55.8716026" , "y" : "-4.2886426"},
        {"x" : "55.8715976" , "y" : "-4.2886447"},
        {"x" : "55.871601" , "y" : "-4.2886716"},
        {"x" : "55.8715873" , "y" : "-4.288678"},
        {"x" : "55.8715838" , "y" : "-4.2886512"},
        {"x" : "55.8715489" , "y" : "-4.2886656"},
        {"x" : "55.8715524" , "y" : "-4.2886922"},
        {"x" : "55.8715389" , "y" : "-4.2886962"},
        {"x" : "55.8715359" , "y" : "-4.2886702"},
        {"x" : "55.8715022" , "y" : "-4.2886842"},
        {"x" : "55.8715058" , "y" : "-4.2887114"},
        {"x" : "55.8714914" , "y" : "-4.2887174"},
        {"x" : "55.8714876" , "y" : "-4.2886887"},
        {"x" : "55.8714526" , "y" : "-4.2887032"},
        {"x" : "55.8714562" , "y" : "-4.2887311"},
        {"x" : "55.8714424" , "y" : "-4.2887368"},
        {"x" : "55.8714388" , "y" : "-4.2887088"},
        {"x" : "55.8714034" , "y" : "-4.2887234"},
        {"x" : "55.8714071" , "y" : "-4.288752"},
        {"x" : "55.8713932" , "y" : "-4.2887578"},
        {"x" : "55.8713894" , "y" : "-4.2887286"},
        {"x" : "55.8713549" , "y" : "-4.288743"},
        {"x" : "55.8713586" , "y" : "-4.2887717"},
        {"x" : "55.8713451" , "y" : "-4.2887773"},
        {"x" : "55.8713412" , "y" : "-4.2887472"},
        {"x" : "55.871335" , "y" : "-4.2887498"},
        {"x" : "55.8713322" , "y" : "-4.2887369"},
        {"x" : "55.8713276" , "y" : "-4.2887262"},
        {"x" : "55.8713214" , "y" : "-4.2887183"},
        {"x" : "55.8713133" , "y" : "-4.2887136"},
        {"x" : "55.8713035" , "y" : "-4.2887144"},
        {"x" : "55.8712641" , "y" : "-4.2887295"},
        {"x" : "55.8712669" , "y" : "-4.2887516"},
        {"x" : "55.8712573" , "y" : "-4.2887553"},
        {"x" : "55.8712545" , "y" : "-4.2887342"},
        {"x" : "55.8712115" , "y" : "-4.2887517"}]},
        {"points": [
        {"x" : "55.8710552" , "y" : "-4.2875629"},
        {"x" : "55.8710569" , "y" : "-4.2875779"},
        {"x" : "55.8710484" , "y" : "-4.2875808"},
        {"x" : "55.8711504" , "y" : "-4.2883728"},
        {"x" : "55.8711606" , "y" : "-4.2883718"},
        {"x" : "55.8711762" , "y" : "-4.2884815"},
        {"x" : "55.8712191" , "y" : "-4.2884626"},
        {"x" : "55.8712169" , "y" : "-4.2884432"},
        {"x" : "55.8712291" , "y" : "-4.2884388"},
        {"x" : "55.8712314" , "y" : "-4.2884583"},
        {"x" : "55.8712665" , "y" : "-4.2884439"},
        {"x" : "55.8712737" , "y" : "-4.2884399"},
        {"x" : "55.8712794" , "y" : "-4.288434"},
        {"x" : "55.8712854" , "y" : "-4.2884231"},
        {"x" : "55.8712896" , "y" : "-4.2884062"},
        {"x" : "55.8712899" , "y" : "-4.2883857"},
        {"x" : "55.8712937" , "y" : "-4.2883842"},
        {"x" : "55.8712893" , "y" : "-4.2883548"},
        {"x" : "55.8713025" , "y" : "-4.2883486"},
        {"x" : "55.8713063" , "y" : "-4.2883778"},
        {"x" : "55.8713429" , "y" : "-4.2883624"},
        {"x" : "55.8713386" , "y" : "-4.2883335"},
        {"x" : "55.8713521" , "y" : "-4.2883278"},
        {"x" : "55.8713561" , "y" : "-4.2883573"},
        {"x" : "55.8713913" , "y" : "-4.2883429"},
        {"x" : "55.8713873" , "y" : "-4.2883134"},
        {"x" : "55.8714003" , "y" : "-4.2883091"},
        {"x" : "55.8714035" , "y" : "-4.2883369"},
        {"x" : "55.8714399" , "y" : "-4.2883212"},
        {"x" : "55.8714365" , "y" : "-4.2882942"},
        {"x" : "55.8714509" , "y" : "-4.2882883"},
        {"x" : "55.8714545" , "y" : "-4.2883158"},
        {"x" : "55.871489" , "y" : "-4.288301"},
        {"x" : "55.8714852" , "y" : "-4.2882727"},
        {"x" : "55.8714985" , "y" : "-4.2882669"},
        {"x" : "55.8715025" , "y" : "-4.2882967"},
        {"x" : "55.871537" , "y" : "-4.2882822"},
        {"x" : "55.8715331" , "y" : "-4.2882544"},
        {"x" : "55.8715472" , "y" : "-4.2882487"},
        {"x" : "55.8715508" , "y" : "-4.2882759"},
        {"x" : "55.8715537" , "y" : "-4.288275"},
        {"x" : "55.8715594" , "y" : "-4.288296"},
        {"x" : "55.8715665" , "y" : "-4.288307"},
        {"x" : "55.871575" , "y" : "-4.2883131"},
        {"x" : "55.871586" , "y" : "-4.288312"},
        {"x" : "55.8715968" , "y" : "-4.2883058"},
        {"x" : "55.8715997" , "y" : "-4.2883072"},
        {"x" : "55.8716883" , "y" : "-4.28827"},
        {"x" : "55.8716726" , "y" : "-4.2881473"},
        {"x" : "55.8716441" , "y" : "-4.2881592"},
        {"x" : "55.8716464" , "y" : "-4.2881769"},
        {"x" : "55.871633" , "y" : "-4.2881825"},
        {"x" : "55.8716297" , "y" : "-4.288157"},
        {"x" : "55.8716164" , "y" : "-4.2881626"},
        {"x" : "55.8716136" , "y" : "-4.288141"},
        {"x" : "55.8716243" , "y" : "-4.2881365"},
        {"x" : "55.8716149" , "y" : "-4.2880655"},
        {"x" : "55.8716044" , "y" : "-4.2880699"},
        {"x" : "55.8716019" , "y" : "-4.2880506"},
        {"x" : "55.871613" , "y" : "-4.2880459"},
        {"x" : "55.871605" , "y" : "-4.2879853"},
        {"x" : "55.8715939" , "y" : "-4.28799"},
        {"x" : "55.8715912" , "y" : "-4.2879699"},
        {"x" : "55.871602" , "y" : "-4.2879654"},
        {"x" : "55.871593" , "y" : "-4.2878973"},
        {"x" : "55.8715829" , "y" : "-4.2879015"},
        {"x" : "55.8715801" , "y" : "-4.2878797"},
        {"x" : "55.8715899" , "y" : "-4.2878756"},
        {"x" : "55.8715811" , "y" : "-4.2878086"},
        {"x" : "55.8715717" , "y" : "-4.2878126"},
        {"x" : "55.8715688" , "y" : "-4.2877909"},
        {"x" : "55.8715787" , "y" : "-4.2877867"},
        {"x" : "55.8715702" , "y" : "-4.2877227"},
        {"x" : "55.8715604" , "y" : "-4.2877268"},
        {"x" : "55.8715575" , "y" : "-4.2877045"},
        {"x" : "55.8715673" , "y" : "-4.2877004"},
        {"x" : "55.8715587" , "y" : "-4.2876352"},
        {"x" : "55.8715488" , "y" : "-4.2876393"},
        {"x" : "55.8715463" , "y" : "-4.2876206"},
        {"x" : "55.8715566" , "y" : "-4.2876163"},
        {"x" : "55.8715475" , "y" : "-4.2875477"},
        {"x" : "55.8715365" , "y" : "-4.2875524"},
        {"x" : "55.8715333" , "y" : "-4.2875286"},
        {"x" : "55.8715467" , "y" : "-4.287523"},
        {"x" : "55.8715438" , "y" : "-4.2875012"},
        {"x" : "55.8715537" , "y" : "-4.2874971"},
        {"x" : "55.8715568" , "y" : "-4.287521"},
        {"x" : "55.8715806" , "y" : "-4.287511"},
        {"x" : "55.8715677" , "y" : "-4.2874103"},
        {"x" : "55.8715709" , "y" : "-4.2874016"},
        {"x" : "55.8715726" , "y" : "-4.2873888"},
        {"x" : "55.8715708" , "y" : "-4.2873736"},
        {"x" : "55.8715653" , "y" : "-4.2873615"},
        {"x" : "55.871558" , "y" : "-4.2873554"},
        {"x" : "55.8715519" , "y" : "-4.2873548"},
        {"x" : "55.8715461" , "y" : "-4.2873576"},
        {"x" : "55.8713766" , "y" : "-4.2874286"},
        {"x" : "55.8713785" , "y" : "-4.2874461"},
        {"x" : "55.8713785" , "y" : "-4.2874625"},
        {"x" : "55.8713743" , "y" : "-4.2874776"},
        {"x" : "55.8713681" , "y" : "-4.287488"},
        {"x" : "55.8713604" , "y" : "-4.287491"},
        {"x" : "55.8713521" , "y" : "-4.2874903"},
        {"x" : "55.8713457" , "y" : "-4.2874823"},
        {"x" : "55.8713408" , "y" : "-4.2874712"},
        {"x" : "55.8713375" , "y" : "-4.2874447"},
        {"x" : "55.8712436" , "y" : "-4.287486"},
        {"x" : "55.8712455" , "y" : "-4.2875044"},
        {"x" : "55.8712455" , "y" : "-4.2875178"},
        {"x" : "55.8712419" , "y" : "-4.2875316"},
        {"x" : "55.8712359" , "y" : "-4.287542"},
        {"x" : "55.8712282" , "y" : "-4.287546"},
        {"x" : "55.8712197" , "y" : "-4.287545"},
        {"x" : "55.8712129" , "y" : "-4.2875376"},
        {"x" : "55.8712065" , "y" : "-4.2875259"},
        {"x" : "55.8712033" , "y" : "-4.2875031"},
        {"x" : "55.8710552" , "y" : "-4.2875629"}]}
      ],
      "Clue": "Known for looking like hogwarts",
       "Information": "The campus was designed by Sir George Gilbert Scott in the Gothic revival style. The largest of these buildings echoed, on a far grander scale, the original High Street campus's twin-quadrangle layout, and may have been inspired by Ypres' late-medieval cloth hall"
      }
   ]
}


